FeSeEL/__init__.py
FeSeEL/config.py
FeSeEL/utils.py
FeSeEL/elimination/__init__.py
FeSeEL/elimination/shap_rfe.py
FeSeEL/selection/__init__.py
FeSeEL/selection/explanatory.py
FeSeEL/selection/multivariate.py
FeSeEL/selection/univariate.py
FeSeEL-1.0.2.dist-info/LICENCE
FeSeEL-1.0.2.dist-info/METADATA
FeSeEL-1.0.2.dist-info/WHEEL
FeSeEL-1.0.2.dist-info/top_level.txt
FeSeEL-1.0.2.dist-info/RECORD
