Metadata-Version: 2.1
Name: FeSeEL
Version: 1.0.2
Summary: Feature Selection and Elimination
Home-page: https://dev.azure.com/credem-data/DAT/_git/FeSTE
Author: DAT/Mattia Centurelli
Author-email: DAT - Mattia Centurelli <mcenturelli@credem.it>
Project-URL: Homepage, https://dev.azure.com/credem-data/DAT/_git/FeSTE
Classifier: Programming Language :: Python :: 3
Classifier: License :: OSI Approved :: MIT License
Classifier: Operating System :: OS Independent
Requires-Python: >=3.8, <4
License-File: LICENCE
Requires-Dist: typed-ast (==1.5.4)
Requires-Dist: numpy (==1.22.4)
Requires-Dist: pandas (==1.4.2)
Requires-Dist: scikit-learn (==1.1.1)
Requires-Dist: lightgbm (==3.3.2)
Requires-Dist: matplotlib (==3.5.2)
Requires-Dist: seaborn (==0.11.1)
Requires-Dist: pyreadstat (==1.1.7)
Requires-Dist: scipy (==1.8.1)
Requires-Dist: statsmodels (==0.13.2)
Requires-Dist: PyYAML (==6.0)
Requires-Dist: shap (==0.38.1)
